{
  "id": "08a5eecf-2b29-495b-931c-034e96b645c1",
  "prevId": "00000000-0000-0000-0000-000000000000",
  "version": "7",
  "dialect": "postgresql",
  "tables": {
    "public.service_title": {
      "name": "service_title",
      "schema": "",
      "columns": {
        "title": {
          "name": "title",
          "type": "text",
          "primaryKey": true,
          "notNull": true
        },
        "description": {
          "name": "description",
          "type": "text",
          "primaryKey": false,
          "notNull": true
        },
        "href": {
          "name": "href",
          "type": "text",
          "primaryKey": false,
          "notNull": true
        },
        "image": {
          "name": "image",
          "type": "text",
          "primaryKey": false,
          "notNull": true
        }
      },
      "indexes": {},
      "foreignKeys": {},
      "compositePrimaryKeys": {},
      "uniqueConstraints": {},
      "policies": {},
      "checkConstraints": {},
      "isRLSEnabled": false
    }
  },
  "enums": {},
  "schemas": {},
  "sequences": {},
  "roles": {},
  "policies": {},
  "views": {},
  "_meta": {
    "columns": {},
    "schemas": {},
    "tables": {}
  }
}